agents/__init__.py
coterie_agents/__init__.py
coterie_agents/audit.py
coterie_agents/authz.py
coterie_agents/command_deck.py
coterie_agents/command_router.py
coterie_agents/logging_config.py
coterie_agents/runtime_guard.py
coterie_agents/test_error.py
coterie_agents/types.py
coterie_agents/types.pyi
coterie_agents/validators.py
coterie_agents/agents/__init__.py
coterie_agents/agents/commands/end_job.py
coterie_agents/agents/commands/memory.py
coterie_agents/bots/__init__.py
coterie_agents/bots/auto_cleaner_bot.py
coterie_agents/bots/logger_bot.py
coterie_agents/bots/reminder_bot.py
coterie_agents/bots/watchdog_bot.py
coterie_agents/commands/__init__.py
coterie_agents/commands/_cli.py
coterie_agents/commands/add_crew.py
coterie_agents/commands/assign.py
coterie_agents/commands/attach.py
coterie_agents/commands/board.py
coterie_agents/commands/book.py
coterie_agents/commands/calendar_auth.py
coterie_agents/commands/clean.py
coterie_agents/commands/cluster_bookings.py
coterie_agents/commands/config.py
coterie_agents/commands/create_persona.py
coterie_agents/commands/dashboard.py
coterie_agents/commands/debug.py
coterie_agents/commands/demote.py
coterie_agents/commands/due.py
coterie_agents/commands/edit_task.py
coterie_agents/commands/email_summary.py
coterie_agents/commands/end_job.py
coterie_agents/commands/exit.py
coterie_agents/commands/generate_invoice.py
coterie_agents/commands/help.py
coterie_agents/commands/help_cmd.py
coterie_agents/commands/history.py
coterie_agents/commands/inventory.py
coterie_agents/commands/list_bookings.py
coterie_agents/commands/list_personas.py
coterie_agents/commands/log.py
coterie_agents/commands/log_job.py
coterie_agents/commands/logger_config.py
coterie_agents/commands/mark.py
coterie_agents/commands/memory.py
coterie_agents/commands/msds.py
coterie_agents/commands/msg.py
coterie_agents/commands/notify.py
coterie_agents/commands/optimize_schedule.py
coterie_agents/commands/process_payment.py
coterie_agents/commands/promote.py
coterie_command_deck-1.0.0.dist-info/METADATA
coterie_command_deck-1.0.0.dist-info/WHEEL
coterie_command_deck-1.0.0.dist-info/entry_points.txt
coterie_command_deck-1.0.0.dist-info/top_level.txt
coterie_command_deck-1.0.0.dist-info/RECORD
