Metadata-Version: 2.4
Name: coterie-command-deck
Version: 1.0.0
Summary: Coterie Command Deck — Wolverine finish
Requires-Python: >=3.12
Provides-Extra: dev
Requires-Dist: pytest>=8.0; extra == "dev"
Requires-Dist: pytest-randomly>=3.15; extra == "dev"
Requires-Dist: mypy>=1.10; extra == "dev"
Requires-Dist: types-requests>=2.31.0.6; extra == "dev"
Requires-Dist: ruff>=0.6.0; extra == "dev"
Requires-Dist: black>=24.8; extra == "dev"
Requires-Dist: pdoc>=14.5; extra == "dev"
Requires-Dist: pytest-cov>=5.0; extra == "dev"
Requires-Dist: python-dotenv>=1.0.0; extra == "dev"
Requires-Dist: google-api-python-client>=2.0.0; extra == "dev"
Requires-Dist: pdfplumber>=0.10.0; extra == "dev"
Requires-Dist: pytesseract>=0.3.10; extra == "dev"
Requires-Dist: pdf2image>=1.16.3; extra == "dev"
Provides-Extra: payments
Requires-Dist: stripe>=10; extra == "payments"
